ironic_inspector_client/__init__.py
ironic_inspector_client/resource.py
ironic_inspector_client/shell.py
ironic_inspector_client/v1.py
ironic_inspector_client/version.py
ironic_inspector_client/common/__init__.py
ironic_inspector_client/common/http.py
ironic_inspector_client/common/i18n.py
ironic_inspector_client/tests/__init__.py
ironic_inspector_client/tests/functional.py
ironic_inspector_client/tests/unit/__init__.py
ironic_inspector_client/tests/unit/test_common_http.py
ironic_inspector_client/tests/unit/test_init.py
ironic_inspector_client/tests/unit/test_shell.py
ironic_inspector_client/tests/unit/test_v1.py
python_ironic_inspector_client-5.4.0.dist-info/AUTHORS
python_ironic_inspector_client-5.4.0.dist-info/LICENSE
python_ironic_inspector_client-5.4.0.dist-info/METADATA
python_ironic_inspector_client-5.4.0.dist-info/WHEEL
python_ironic_inspector_client-5.4.0.dist-info/entry_points.txt
python_ironic_inspector_client-5.4.0.dist-info/pbr.json
python_ironic_inspector_client-5.4.0.dist-info/top_level.txt
python_ironic_inspector_client-5.4.0.dist-info/RECORD
