Metadata-Version: 2.1
Name: python-ironic-inspector-client
Version: 5.4.0
Summary: Python client for Ironic Inspector
Home-page: https://docs.openstack.org/python-ironic-inspector-client/latest/
Author: OpenStack
Author-email: openstack-discuss@lists.openstack.org
License: Apache-2.0
Classifier: Environment :: Console
Classifier: Environment :: OpenStack
Classifier: Intended Audience :: Developers
Classifier: Intended Audience :: Information Technology
Classifier: Operating System :: OS Independent
Classifier: Programming Language :: Python
Classifier: Programming Language :: Python :: Implementation :: CPython
Classifier: Programming Language :: Python :: 3 :: Only
Classifier: Programming Language :: Python :: 3
Classifier: Programming Language :: Python :: 3.10
Classifier: Programming Language :: Python :: 3.11
Classifier: Programming Language :: Python :: 3.12
Requires-Python: >=3.10
License-File: LICENSE
License-File: AUTHORS
Requires-Dist: cliff>=2.8.0
Requires-Dist: keystoneauth1>=3.4.0
Requires-Dist: pbr>=2.0.0
Requires-Dist: PyYAML>=3.13
Requires-Dist: requests>=2.14.2
Provides-Extra: cli
Requires-Dist: python-openstackclient>=3.12.0; extra == "cli"
Provides-Extra: test
Requires-Dist: coverage>=5.0; extra == "test"
Requires-Dist: fixtures>=3.0.0; extra == "test"
Requires-Dist: requests-mock>=1.2.0; extra == "test"
Requires-Dist: oslo.concurrency>=3.25.0; extra == "test"
Requires-Dist: osc-lib>=2.1.0; extra == "test"
Requires-Dist: python-openstackclient>=3.12.0; extra == "test"
Requires-Dist: stestr>=2.0.0; extra == "test"
